bib/__init__.py
bib/bib_watch.py
bib_watch-1.0.2.dist-info/METADATA
bib_watch-1.0.2.dist-info/WHEEL
bib_watch-1.0.2.dist-info/entry_points.txt
bib_watch-1.0.2.dist-info/top_level.txt
bib_watch-1.0.2.dist-info/RECORD
