Metadata-Version: 2.1
Name: bib-watch
Version: 1.0.2
Summary: A LaTeX bibliography manager that automatically organizes references
Home-page: https://github.com/yourusername/bibmanager
Author: Your Name
Author-email: your.email@example.com
Classifier: Programming Language :: Python :: 3
Classifier: License :: OSI Approved :: MIT License
Classifier: Operating System :: OS Independent
Requires-Python: >=3.6
Requires-Dist: bibtexparser
Requires-Dist: watchdog
